altex_be/bed_for_ucsc_custom_track_maker.py
altex_be/class_def/base_editors.py
altex_be/gtf2refflat_converter.py
altex_be/logging_config.py
altex_be/main.py
altex_be/manage_arguments/build_parser.py
altex_be/manage_arguments/crispr_direct_supported_assemblies.txt
altex_be/manage_arguments/parse_arguments.py
altex_be/manage_arguments/validate_arguments.py
altex_be/offtarget_scorer.py
altex_be/output_formatter.py
altex_be/refflat_preprocessor.py
altex_be/sequence_annotator.py
altex_be/sgrna_designer.py
altex_be/splicing_event_classifier.py
altex_be/target_exon_extractor.py
altex_be-1.0.5.dist-info/METADATA
altex_be-1.0.5.dist-info/WHEEL
altex_be-1.0.5.dist-info/entry_points.txt
altex_be-1.0.5.dist-info/licenses/LICENSE.md
altex_be-1.0.5.dist-info/RECORD
