Metadata-Version: 2.4
Name: AltEx-BE
Version: 1.0.5
Summary: automatically design sgRNA for exon skipping with many base editors
License: MIT
License-File: LICENSE.md
Author: Kinari Matsumoto
Author-email: matsumoto.kinari.qm@alumni.tsukuba.ac.jp
Requires-Python: >=3.12,<4.0
Classifier: Intended Audience :: Science/Research
Classifier: License :: OSI Approved :: MIT License
Classifier: Operating System :: MacOS
Classifier: Operating System :: POSIX :: Linux
Classifier: Programming Language :: Python :: 3
Classifier: Programming Language :: Python :: 3.12
Classifier: Programming Language :: Python :: 3.13
Classifier: Programming Language :: Python :: 3.14
Classifier: Topic :: Scientific/Engineering :: Bio-Informatics
Requires-Dist: pandas (>=2.3.0,<3.0.0)
Requires-Dist: pyahocorasick (>=2.2.0,<3.0.0)
Requires-Dist: pybedtools (>=0.12.0,<0.13.0)
Requires-Dist: tqdm (>=4.67.1,<5.0.0)
Project-URL: Homepage, https://github.com/kinari-labwork/AltEx-BE
